rustlike/__init__.py
rustlike/base_exception.py
rustlike/rustlike.py
rustlike-0.2.1.dist-info/WHEEL
rustlike-0.2.1.dist-info/METADATA
rustlike-0.2.1.dist-info/RECORD
