Metadata-Version: 2.1
Name: rustlike
Version: 0.2.1
Summary: Rust-like API in Python
License: MIT
Author: Josh Wycuff
Author-email: Joshua.Wycuff@turner.com
Requires-Python: >=3.6,<4
Classifier: License :: OSI Approved :: MIT License
Classifier: Programming Language :: Python :: 3
Classifier: Programming Language :: Python :: 3.6
Classifier: Programming Language :: Python :: 3.7
Classifier: Programming Language :: Python :: 3.8
Classifier: Programming Language :: Python :: 3.9
Classifier: Programming Language :: Python :: 3.10
